{
  "hash": "65972ae2be4f12a4d6cd202c8b3361d7",
  "result": {
    "engine": "knitr",
    "markdown": "---\ntitle: 'Data: Overture'\nsubtitle: 'Welcome to #30DayMapChallenge 2024 Day 29'\ndate: '2024-11-29'\nimage: 'https://raw.githubusercontent.com/Fgazzelloni/30DayMapChallenge/master/2024/day29_overture/day29_overture.png'\nimage-alt: 'day29_overture'\ndescription: 'Data: Overture'\noutput: html_document\nexecute: \n   eval: false\n---\n\n\n\n\n![Data: Overture](https://raw.githubusercontent.com/Fgazzelloni/30DayMapChallenge/master/2024/day29_overture/day29_overture.png)\n\nData Source: <https://explore.overturemaps.org/#15.73/48.8552/2.3417/15.3/12>\n\n\n\n::: {.cell}\n\n```{.r .cell-code}\nlibrary(tidyverse)\nlibrary(sf)\n```\n:::\n\n::: {.cell}\n\n```{.r .cell-code}\n# Replace the path with your GeoJSON file location\ngeojson_file <- \"data/overture-15.73-48.855200000000735-2.3417000000001735.geojson\"\n\n# Read the GeoJSON file as an sf object\ngeo_data <- st_read(geojson_file)\n```\n:::\n\n::: {.cell}\n\n```{.r .cell-code}\nlibrary(showtext)\n\nfont_add_google(name = 'Parisienne', \n                family = 'Parisienne', \n                bold.wt = 800)\nfont_add_google(name = 'Tinos', \n                family = 'Tinos', \n                regular.wt = 400, \n                bold.wt = 700)\nshowtext_auto()\n```\n:::\n\n::: {.cell}\n\n```{.r .cell-code}\ngeo_data %>%\n  mutate(num_floors= as.factor(num_floors)) %>%\n  ggplot() +\n  geom_sf(aes(fill=num_floors)) +\n  #scale_fill_discrete(na.value = 'grey90')+\n  scico::scale_fill_scico_d(palette = 'batlow', \n                            na.value = 'grey90')+\n  labs(title = \"Paris Road Network\",\n       subtitle = \"Buildings with Number of Floors - Data from Overturemaps.org\",\n       caption = \"Data Source: Overture Maps\\n#30DayMapChallenge Day29 | @fgazzelloni\",\n       fill= \"Number of Floors\",\n       x = \"Longitude\",\n       y = \"Latitude\") +\n  theme_minimal()+\n  theme(text = element_text(family = \"Parisienne\", size=40),\n        plot.background = element_rect(fill = \"grey20\",color=NA),\n        panel.background = element_rect(fill = \"grey20\",color=NA),\n        plot.title = element_text(color = \"white\",\n                                  size=100,\n                                  hjust=0.5),\n        plot.subtitle = element_text(color = \"white\",\n                                     size=50,\n                                     hjust=0.5),\n        plot.caption = element_text(color = \"white\",\n                                    size=40,\n                                    lineheight=0.4,\n                                    hjust=0.5),\n        axis.title = element_text(color = \"white\"),\n        axis.text = element_text(color = \"white\", family = \"Tinos\"),\n        panel.grid = element_line(color = \"grey40\"),\n        legend.title = element_text(color = \"white\"),\n        legend.text = element_text(color = \"white\"))\n```\n:::\n\n\n\nsave it as png\n\n\n\n::: {.cell}\n\n```{.r .cell-code}\nggsave(\"day29_overture.png\", \n       width = 10, height = 8, \n       units = \"in\", \n       dpi = 300)\n```\n:::\n",
    "supporting": [],
    "filters": [
      "rmarkdown/pagebreak.lua"
    ],
    "includes": {},
    "engineDependencies": {},
    "preserve": {},
    "postProcess": true
  }
}